overseerr_api/__init__.py
overseerr_api/api_client.py
overseerr_api/api_response.py
overseerr_api/configuration.py
overseerr_api/exceptions.py
overseerr_api/py.typed
overseerr_api/rest.py
overseerr_api/api/__init__.py
overseerr_api/api/auth_api.py
overseerr_api/api/collection_api.py
overseerr_api/api/issue_api.py
overseerr_api/api/media_api.py
overseerr_api/api/movies_api.py
overseerr_api/api/other_api.py
overseerr_api/api/person_api.py
overseerr_api/api/public_api.py
overseerr_api/api/request_api.py
overseerr_api/api/search_api.py
overseerr_api/api/service_api.py
overseerr_api/api/settings_api.py
overseerr_api/api/tmdb_api.py
overseerr_api/api/tv_api.py
overseerr_api/api/users_api.py
overseerr_api/models/__init__.py
overseerr_api/models/auth_local_post_request.py
overseerr_api/models/auth_logout_post200_response.py
overseerr_api/models/auth_plex_post_request.py
overseerr_api/models/auth_reset_password_guid_post_request.py
overseerr_api/models/auth_reset_password_post_request.py
overseerr_api/models/cast.py
overseerr_api/models/collection.py
overseerr_api/models/company.py
overseerr_api/models/credit_cast.py
overseerr_api/models/credit_crew.py
overseerr_api/models/crew.py
overseerr_api/models/discord_settings.py
overseerr_api/models/discord_settings_options.py
overseerr_api/models/discover_genreslider_movie_get200_response_inner.py
overseerr_api/models/discover_keyword_keyword_id_movies_get200_response.py
overseerr_api/models/discover_movies_genre_genre_id_get200_response.py
overseerr_api/models/discover_movies_language_language_get200_response.py
overseerr_api/models/discover_movies_studio_studio_id_get200_response.py
overseerr_api/models/discover_slider.py
overseerr_api/models/discover_trending_get200_response.py
overseerr_api/models/discover_trending_get200_response_results_inner.py
overseerr_api/models/discover_tv_genre_genre_id_get200_response.py
overseerr_api/models/discover_tv_get200_response.py
overseerr_api-1.0.1.dist-info/METADATA
overseerr_api-1.0.1.dist-info/WHEEL
overseerr_api-1.0.1.dist-info/top_level.txt
overseerr_api-1.0.1.dist-info/RECORD
