Metadata-Version: 2.1
Name: overseerr-api
Version: 1.0.1
Summary: Overseerr API
Home-page: 
Author: OpenAPI Generator community
Author-email: team@openapitools.org
Keywords: OpenAPI,OpenAPI-Generator,Overseerr API
Requires-Dist: urllib3 <2.1.0,>=1.25.3
Requires-Dist: python-dateutil
Requires-Dist: pydantic <2,>=1.10.5
Requires-Dist: aenum
